sponge_docs_theme/__init__.py
sponge_docs_theme/context.py
sponge_docs_theme/favicon.ico
sponge_docs_theme/helpers.py
sponge_docs_theme/languages.json
sponge_docs_theme/languages.py
sponge_docs_theme/theme.pot
sponge_docs_theme/theme.py
sponge_docs_theme/extra/worker.js
sponge_docs_theme/static/jszip.js
sponge_docs_theme/static/ore.svg
sponge_docs_theme/static/spongedocs.css
sponge_docs_theme/static/spongedocs.js
sponge_docs_theme/static/spongie-mark-dark.svg
sponge_docs_theme/static/flags/af_ZA.svg
sponge_docs_theme/static/flags/ar_SA.svg
sponge_docs_theme/static/flags/bg_BG.svg
sponge_docs_theme/static/flags/ca_ES.svg
sponge_docs_theme/static/flags/cs_CZ.svg
sponge_docs_theme/static/flags/da_DK.svg
sponge_docs_theme/static/flags/de_DE.svg
sponge_docs_theme/static/flags/el_GR.svg
sponge_docs_theme/static/flags/en.svg
sponge_docs_theme/static/flags/en_GB.svg
sponge_docs_theme/static/flags/en_PT.svg
sponge_docs_theme/static/flags/es_ES.svg
sponge_docs_theme/static/flags/fi_FI.svg
sponge_docs_theme/static/flags/fr_FR.svg
sponge_docs_theme/static/flags/he_IL.svg
sponge_docs_theme/static/flags/hu_HU.svg
sponge_docs_theme/static/flags/id_ID.svg
sponge_docs_theme/static/flags/it_IT.svg
sponge_docs_theme/static/flags/ja_JP.svg
sponge_docs_theme/static/flags/ko_KR.svg
sponge_docs_theme/static/flags/lt_LT.svg
sponge_docs_theme/static/flags/nb_NO.svg
sponge_docs_theme/static/flags/nl_NL.svg
sponge_docs_theme/static/flags/no_NO.svg
sponge_docs_theme/static/flags/pl_PL.svg
sponge_docs_theme/static/flags/pt_BR.svg
sponge_docs_theme/static/flags/pt_PT.svg
sponge_docs_theme/static/flags/ro_RO.svg
sponge_docs_theme/static/flags/ru_RU.svg
sponge_docs_theme/static/flags/sr_SP.svg
sponge_docs_theme/static/flags/sv_SE.svg
sponge_docs_theme/static/flags/tr_TR.svg
sponge_docs_theme/static/flags/uk_UA.svg
sponge_docs_theme/static/flags/vi_VN.svg
sponge_docs_theme/static/flags/zh_CN.svg
sponge_docs_theme/static/flags/zh_TW.svg
sponge_docs_theme/static/fonts/OFL.txt
sponge_docs_theme-1.1.0.dist-info/LICENSE.txt
sponge_docs_theme-1.1.0.dist-info/METADATA
sponge_docs_theme-1.1.0.dist-info/WHEEL
sponge_docs_theme-1.1.0.dist-info/top_level.txt
sponge_docs_theme-1.1.0.dist-info/RECORD
