Metadata-Version: 2.1
Name: sponge-docs-theme
Version: 1.1.0
Summary: Theme for Sponge documentation
Home-page: https://github.com/SpongePowered/sponge-docs-theme
Author: SpongePowered
License: MIT
Platform: UNKNOWN
Classifier: Development Status :: 5 - Production/Stable
Classifier: License :: OSI Approved :: MIT License
Classifier: Programming Language :: Python :: 3
Classifier: Framework :: Sphinx
Classifier: Framework :: Sphinx :: Extension
License-File: LICENSE.txt
Requires-Dist: sphinx-rtd-theme (==1.0.0)
